bittrade_huobi_websocket/__init__.py
bittrade_huobi_websocket/channels/__init__.py
bittrade_huobi_websocket/channels/account_change.py
bittrade_huobi_websocket/channels/message.py
bittrade_huobi_websocket/channels/open_orders.py
bittrade_huobi_websocket/channels/orderbook.py
bittrade_huobi_websocket/channels/subscribe.py
bittrade_huobi_websocket/channels/trade.py
bittrade_huobi_websocket/connection/__init__.py
bittrade_huobi_websocket/connection/connection_operators.py
bittrade_huobi_websocket/connection/generic.py
bittrade_huobi_websocket/connection/http.py
bittrade_huobi_websocket/connection/private.py
bittrade_huobi_websocket/connection/public.py
bittrade_huobi_websocket/connection/reconnect.py
bittrade_huobi_websocket/connection/request_response.py
bittrade_huobi_websocket/events/__init__.py
bittrade_huobi_websocket/events/ids.py
bittrade_huobi_websocket/events/models/__init__.py
bittrade_huobi_websocket/events/models/order.py
bittrade_huobi_websocket/framework/__init__.py
bittrade_huobi_websocket/framework/context_manager.py
bittrade_huobi_websocket/framework/framework.py
bittrade_huobi_websocket/framework/sign.py
bittrade_huobi_websocket/messages/__init__.py
bittrade_huobi_websocket/messages/filters/__init__.py
bittrade_huobi_websocket/messages/filters/kind.py
bittrade_huobi_websocket/messages/heartbeat.py
bittrade_huobi_websocket/messages/json.py
bittrade_huobi_websocket/messages/listen.py
bittrade_huobi_websocket/models/__init__.py
bittrade_huobi_websocket/models/book.py
bittrade_huobi_websocket/models/currency_networks.py
bittrade_huobi_websocket/models/endpoints.py
bittrade_huobi_websocket/models/enhanced_websocket.py
bittrade_huobi_websocket/models/framework.py
bittrade_huobi_websocket/models/order.py
bittrade_huobi_websocket/models/request.py
bittrade_huobi_websocket/models/response_message.py
bittrade_huobi_websocket/models/rest/__init__.py
bittrade_huobi_websocket/models/rest/account_account_history.py
bittrade_huobi_websocket-0.3.8.dist-info/METADATA
bittrade_huobi_websocket-0.3.8.dist-info/WHEEL
bittrade_huobi_websocket-0.3.8.dist-info/RECORD
